maestral_qt/__init__.py
maestral_qt/__main__.py
maestral_qt/activity_window.py
maestral_qt/autostart.py
maestral_qt/bandwidth_dialog.py
maestral_qt/dropbox_location_dialog.py
maestral_qt/main.py
maestral_qt/relink_dialog.py
maestral_qt/selective_sync_dialog.py
maestral_qt/settings_window.py
maestral_qt/setup_dialog.py
maestral_qt/sync_issues_window.py
maestral_qt/utils.py
maestral_qt/widgets.py
maestral_qt/__pyinstaller/__init__.py
maestral_qt/__pyinstaller/hook-maestral_qt.py
maestral_qt/resources/__init__.py
maestral_qt/resources/faceholder.png
maestral_qt/resources/file
maestral_qt/resources/maestral.desktop
maestral_qt/resources/maestral.icns
maestral_qt/resources/maestral.png
maestral_qt/resources/maestral_tray-disconnected-dark.svg
maestral_qt/resources/maestral_tray-disconnected-light.svg
maestral_qt/resources/maestral_tray-error-dark.svg
maestral_qt/resources/maestral_tray-error-light.svg
maestral_qt/resources/maestral_tray-idle-dark.svg
maestral_qt/resources/maestral_tray-idle-light.svg
maestral_qt/resources/maestral_tray-info-dark.svg
maestral_qt/resources/maestral_tray-info-light.svg
maestral_qt/resources/maestral_tray-paused-dark.svg
maestral_qt/resources/maestral_tray-paused-light.svg
maestral_qt/resources/maestral_tray-syncing-dark.svg
maestral_qt/resources/maestral_tray-syncing-light.svg
maestral_qt/resources/ui_bandwidth_dialog.py
maestral_qt/resources/ui_dropbox_location_dialog.py
maestral_qt/resources/ui_relink_dialog.py
maestral_qt/resources/ui_selective_sync_dialog.py
maestral_qt/resources/ui_settings_window.py
maestral_qt/resources/ui_setup_dialog.py
maestral_qt/resources/ui_sync_event_widget.py
maestral_qt/resources/ui_sync_issue_widget.py
maestral_qt/resources/ui_sync_issues_window.py
maestral_qt/resources/ui_unlink_dialog.py
maestral_qt-1.9.8.data/data/share/applications/maestral.desktop
maestral_qt-1.9.8.data/data/share/icons/maestral.png
maestral_qt-1.9.8.dist-info/licenses/LICENSE.txt
maestral_qt-1.9.8.dist-info/METADATA
maestral_qt-1.9.8.dist-info/WHEEL
maestral_qt-1.9.8.dist-info/entry_points.txt
maestral_qt-1.9.8.dist-info/top_level.txt
maestral_qt-1.9.8.dist-info/RECORD
