Metadata-Version: 2.4
Name: maestral-qt
Version: 1.9.8
Summary: A Qt GUI for the Maestral daemon
Home-page: https://maestral.app
Author: Sam Schott
Author-email: sam.schott@outlook.com
License: MIT
Classifier: License :: OSI Approved :: MIT License
Classifier: Operating System :: Unix
Classifier: Programming Language :: Python
Classifier: Programming Language :: Python :: 3
Classifier: Programming Language :: Python :: 3.7
Classifier: Programming Language :: Python :: 3.8
Classifier: Programming Language :: Python :: 3.9
Classifier: Programming Language :: Python :: 3.10
Classifier: Programming Language :: Python :: 3.11
Classifier: Programming Language :: Python :: 3 :: Only
Requires-Python: >=3.7
License-File: LICENSE.txt
Requires-Dist: click>=7.1.1
Requires-Dist: maestral>=1.9.6
Requires-Dist: markdown2
Requires-Dist: packaging
Requires-Dist: PyQt6
Dynamic: license-file
